browserpilot/agents/__init__.py
browserpilot/agents/compilers/instruction_compiler.py
browserpilot/agents/gpt_selenium_agent.py
browserpilot/agents/memories/__init__.py
browserpilot-0.2.53.dist-info/LICENSE
browserpilot-0.2.53.dist-info/METADATA
browserpilot-0.2.53.dist-info/WHEEL
browserpilot-0.2.53.dist-info/RECORD
