Metadata-Version: 2.1
Name: browserpilot
Version: 0.2.53
Summary: Natural language browser automation
Author: Andrew Han
Author-email: handrew11@gmail.com
Requires-Python: >=3.10,<4.0
Classifier: Programming Language :: Python :: 3
Classifier: Programming Language :: Python :: 3.10
Classifier: Programming Language :: Python :: 3.11
Classifier: Programming Language :: Python :: 3.12
Requires-Dist: beautifulsoup4 (>=4.12.3,<5.0.0)
Requires-Dist: click (>=8.1.7,<9.0.0)
Requires-Dist: langchain (>=0.1.20,<0.2.0)
Requires-Dist: langchain_openai (>=0.1.7,<0.2.0)
Requires-Dist: llama-index (>=0.10.68,<0.11.0)
Requires-Dist: openai (>=1.55.0,<2.0.0)
Requires-Dist: pyyaml (>=6.0.2,<7.0.0)
Requires-Dist: selenium (>=4.26.1,<5.0.0)
Requires-Dist: tqdm (>=4.67.0,<5.0.0)
